<?xml version="1.0" ?>
<spritefont version="1.0" texture="jp_font_8x8.png" font_size="8" default="?" kerning-x="0" kerning-y="6" kerning-z="8">
  <characters>
	<!-- EXPLANTION
		x= pixel horizontal coordinate where character starts
		y = pixel vertical coordinate where character starts
		width/height = size in pixels
		char= the character represented
		left = The left-side bearing, i.e., the horizontal distance     
					from the current pen position to the left border of the  
					glyph bitmap.     
		top    :: The top-side bearing, i.e., the vertical distance from   
                the current pen position to the top border of the glyph  
                bitmap.  This distance is positive for upwards~y!  
		horiadvance= Advance width for horizontal layout
		
		https://www.freetype.org/freetype2/docs/glyphs/glyphs-3.html
	-->
    <rectangle x="0" y="0" width="8" height="8" char="Ａ" left="0" top="0" horiadvance="0" />
     <rectangle x="8" y="0" width="8" height="8" char="Ｂ" left="0" top="0" horiadvance="0" />
     <rectangle x="16" y="0" width="8" height="8" char="Ｃ" left="0" top="0" horiadvance="0" />
     <rectangle x="24" y="0" width="8" height="8" char="Ｄ" left="0" top="0" horiadvance="0" />
     <rectangle x="32" y="0" width="8" height="8" char="Ｅ" left="0" top="0" horiadvance="0" />
     <rectangle x="40" y="0" width="8" height="8" char="Ｆ" left="0" top="0" horiadvance="0" />
     <rectangle x="48" y="0" width="8" height="8" char="Ｇ" left="0" top="0" horiadvance="0" />
     <rectangle x="56" y="0" width="8" height="8" char="Ｈ" left="0" top="0" horiadvance="0" />
     <rectangle x="64" y="0" width="8" height="8" char="Ｉ" left="0" top="0" horiadvance="0" />
     <rectangle x="72" y="0" width="8" height="8" char="Ｊ" left="0" top="0" horiadvance="0" />
     <rectangle x="80" y="0" width="8" height="8" char="Ｋ" left="0" top="0" horiadvance="0" />
     <rectangle x="88" y="0" width="8" height="8" char="Ｌ" left="0" top="0" horiadvance="0" />
     <rectangle x="96" y="0" width="8" height="8" char="Ｍ" left="0" top="0" horiadvance="0" />
     <rectangle x="104" y="0" width="8" height="8" char="Ｎ" left="0" top="0" horiadvance="0" />
     <rectangle x="112" y="0" width="8" height="8" char="Ｏ" left="0" top="0" horiadvance="0" />
     <rectangle x="120" y="0" width="8" height="8" char="Ｐ" left="0" top="0" horiadvance="0" />
     <rectangle x="0" y="8" width="8" height="8" char="Ｑ" left="0" top="0" horiadvance="0" />
     <rectangle x="8" y="8" width="8" height="8" char="Ｒ" left="0" top="0" horiadvance="0" />
     <rectangle x="16" y="8" width="8" height="8" char="Ｓ" left="0" top="0" horiadvance="0" />
     <rectangle x="24" y="8" width="8" height="8" char="Ｔ" left="0" top="0" horiadvance="0" />
     <rectangle x="32" y="8" width="8" height="8" char="Ｕ" left="0" top="0" horiadvance="0" />
     <rectangle x="40" y="8" width="8" height="8" char="Ｖ" left="0" top="0" horiadvance="0" />
     <rectangle x="48" y="8" width="8" height="8" char="Ｗ" left="0" top="0" horiadvance="0" />
     <rectangle x="56" y="8" width="8" height="8" char="Ｘ" left="0" top="0" horiadvance="0" />
     <rectangle x="64" y="8" width="8" height="8" char="Ｙ" left="0" top="0" horiadvance="0" />
     <rectangle x="72" y="8" width="8" height="8" char="Ｚ" left="0" top="0" horiadvance="0" />
     <rectangle x="80" y="8" width="8" height="8" char="ａ" left="0" top="0" horiadvance="0" />
     <rectangle x="88" y="8" width="8" height="8" char="ｂ" left="0" top="0" horiadvance="0" />
     <rectangle x="96" y="8" width="8" height="8" char="ｃ" left="0" top="0" horiadvance="0" />
     <rectangle x="104" y="8" width="8" height="8" char="ｄ" left="0" top="0" horiadvance="0" />
     <rectangle x="112" y="8" width="8" height="8" char="ｅ" left="0" top="0" horiadvance="0" />
     <rectangle x="120" y="8" width="8" height="8" char="ｆ" left="0" top="0" horiadvance="0" />
     <rectangle x="0" y="16" width="8" height="8" char="ｇ" left="0" top="0" horiadvance="0" />
     <rectangle x="8" y="16" width="8" height="8" char="ｈ" left="0" top="0" horiadvance="0" />
     <rectangle x="16" y="16" width="8" height="8" char="ｉ" left="0" top="0" horiadvance="0" />
     <rectangle x="24" y="16" width="8" height="8" char="ｊ" left="0" top="0" horiadvance="0" />
     <rectangle x="32" y="16" width="8" height="8" char="ｋ" left="0" top="0" horiadvance="0" />
     <rectangle x="40" y="16" width="8" height="8" char="ｌ" left="0" top="0" horiadvance="0" />
     <rectangle x="48" y="16" width="8" height="8" char="ｍ" left="0" top="0" horiadvance="0" />
     <rectangle x="56" y="16" width="8" height="8" char="ｎ" left="0" top="0" horiadvance="0" />
     <rectangle x="64" y="16" width="8" height="8" char="ｏ" left="0" top="0" horiadvance="0" />
     <rectangle x="72" y="16" width="8" height="8" char="ｐ" left="0" top="0" horiadvance="0" />
     <rectangle x="80" y="16" width="8" height="8" char="ｑ" left="0" top="0" horiadvance="0" />
     <rectangle x="88" y="16" width="8" height="8" char="ｒ" left="0" top="0" horiadvance="0" />
     <rectangle x="96" y="16" width="8" height="8" char="ｓ" left="0" top="0" horiadvance="0" />
     <rectangle x="104" y="16" width="8" height="8" char="ｔ" left="0" top="0" horiadvance="0" />
     <rectangle x="112" y="16" width="8" height="8" char="ｕ" left="0" top="0" horiadvance="0" />
     <rectangle x="120" y="16" width="8" height="8" char="ｖ" left="0" top="0" horiadvance="0" />
     <rectangle x="0" y="24" width="8" height="8" char="ｗ" left="0" top="0" horiadvance="0" />
     <rectangle x="8" y="24" width="8" height="8" char="ｘ" left="0" top="0" horiadvance="0" />
     <rectangle x="16" y="24" width="8" height="8" char="ｙ" left="0" top="0" horiadvance="0" />
     <rectangle x="24" y="24" width="8" height="8" char="ｚ" left="0" top="0" horiadvance="0" />
     <rectangle x="32" y="24" width="8" height="8" char="０" left="0" top="0" horiadvance="0" />
     <rectangle x="40" y="24" width="8" height="8" char="１" left="0" top="0" horiadvance="0" />
     <rectangle x="48" y="24" width="8" height="8" char="２" left="0" top="0" horiadvance="0" />
     <rectangle x="56" y="24" width="8" height="8" char="３" left="0" top="0" horiadvance="0" />
     <rectangle x="64" y="24" width="8" height="8" char="４" left="0" top="0" horiadvance="0" />
     <rectangle x="72" y="24" width="8" height="8" char="５" left="0" top="0" horiadvance="0" />
     <rectangle x="80" y="24" width="8" height="8" char="６" left="0" top="0" horiadvance="0" />
     <rectangle x="88" y="24" width="8" height="8" char="７" left="0" top="0" horiadvance="0" />
     <rectangle x="96" y="24" width="8" height="8" char="８" left="0" top="0" horiadvance="0" />
     <rectangle x="104" y="24" width="8" height="8" char="９" left="0" top="0" horiadvance="0" />
     <rectangle x="112" y="24" width="8" height="8" char="、" left="0" top="0" horiadvance="0" />
     <rectangle x="120" y="24" width="8" height="8" char="。" left="0" top="0" horiadvance="0" />
     <rectangle x="0" y="32" width="8" height="8" char="・" left="0" top="0" horiadvance="0" />
     <rectangle x="8" y="32" width="8" height="8" char="：" left="0" top="0" horiadvance="0" />
     <rectangle x="16" y="32" width="8" height="8" char="；" left="0" top="0" horiadvance="0" />
     <rectangle x="24" y="32" width="8" height="8" char="？" left="0" top="0" horiadvance="0" />
     <rectangle x="32" y="32" width="8" height="8" char="！" left="0" top="0" horiadvance="0" />
     <rectangle x="40" y="32" width="8" height="8" char="ー" left="0" top="0" horiadvance="0" />
     <rectangle x="48" y="32" width="8" height="8" char="/" left="0" top="0" horiadvance="0" />
     <rectangle x="56" y="32" width="8" height="8" char="…" left="0" top="0" horiadvance="0" />
     <rectangle x="64" y="32" width="8" height="8" char="（" left="0" top="0" horiadvance="0" />
     <rectangle x="72" y="32" width="8" height="8" char="）" left="0" top="0" horiadvance="0" />
     <rectangle x="80" y="32" width="8" height="8" char="＜" left="0" top="0" horiadvance="0" />
     <rectangle x="88" y="32" width="8" height="8" char="＞" left="0" top="0" horiadvance="0" />
     <rectangle x="96" y="32" width="8" height="8" char="「" left="0" top="0" horiadvance="0" />
     <rectangle x="104" y="32" width="8" height="8" char="」" left="0" top="0" horiadvance="0" />
     <rectangle x="112" y="32" width="8" height="8" char="【" left="0" top="0" horiadvance="0" />
     <rectangle x="120" y="32" width="8" height="8" char="】" left="0" top="0" horiadvance="0" />
     <rectangle x="0" y="40" width="8" height="8" char="＋" left="0" top="0" horiadvance="0" />
     <rectangle x="8" y="40" width="8" height="8" char="－" left="0" top="0" horiadvance="0" />
     <rectangle x="16" y="40" width="8" height="8" char="＝" left="0" top="0" horiadvance="0" />
     <rectangle x="24" y="40" width="8" height="8" char="％" left="0" top="0" horiadvance="0" />
     <rectangle x="32" y="40" width="8" height="8" char="＃" left="0" top="0" horiadvance="0" />
     <rectangle x="40" y="40" width="8" height="8" char="＄" left="0" top="0" horiadvance="0" />
     <rectangle x="48" y="40" width="8" height="8" char="＆" left="0" top="0" horiadvance="0" />
     <rectangle x="56" y="40" width="8" height="8" char="＊" left="0" top="0" horiadvance="0" />
     <rectangle x="64" y="40" width="8" height="8" char="○" left="0" top="0" horiadvance="0" />
     <rectangle x="72" y="40" width="8" height="8" char="※" left="0" top="0" horiadvance="0" />
     <rectangle x="80" y="40" width="8" height="8" char="←" left="0" top="0" horiadvance="0" />
     <rectangle x="88" y="40" width="8" height="8" char="→" left="0" top="0" horiadvance="0" />
     <rectangle x="96" y="40" width="8" height="8" char="↑" left="0" top="0" horiadvance="0" />
     <rectangle x="104" y="40" width="8" height="8" char="↓" left="0" top="0" horiadvance="0" />
     <rectangle x="112" y="40" width="8" height="8" char="①" left="0" top="0" horiadvance="0" />
     <rectangle x="120" y="40" width="8" height="8" char="②" left="0" top="0" horiadvance="0" />
     <rectangle x="0" y="48" width="8" height="8" char="③" left="0" top="0" horiadvance="0" />
     <rectangle x="8" y="48" width="8" height="8" char="④" left="0" top="0" horiadvance="0" />
     <rectangle x="16" y="48" width="8" height="8" char="⑤" left="0" top="0" horiadvance="0" />
     <rectangle x="24" y="48" width="8" height="8" char="⑥" left="0" top="0" horiadvance="0" />
     <rectangle x="32" y="48" width="8" height="8" char="　" left="0" top="0" horiadvance="0" />
     <rectangle x="40" y="48" width="8" height="8" char="あ" left="0" top="0" horiadvance="0" />
     <rectangle x="48" y="48" width="8" height="8" char="い" left="0" top="0" horiadvance="0" />
     <rectangle x="56" y="48" width="8" height="8" char="う" left="0" top="0" horiadvance="0" />
     <rectangle x="64" y="48" width="8" height="8" char="え" left="0" top="0" horiadvance="0" />
     <rectangle x="72" y="48" width="8" height="8" char="お" left="0" top="0" horiadvance="0" />
     <rectangle x="80" y="48" width="8" height="8" char="か" left="0" top="0" horiadvance="0" />
     <rectangle x="88" y="48" width="8" height="8" char="き" left="0" top="0" horiadvance="0" />
     <rectangle x="96" y="48" width="8" height="8" char="く" left="0" top="0" horiadvance="0" />
     <rectangle x="104" y="48" width="8" height="8" char="け" left="0" top="0" horiadvance="0" />
     <rectangle x="112" y="48" width="8" height="8" char="こ" left="0" top="0" horiadvance="0" />
     <rectangle x="120" y="48" width="8" height="8" char="さ" left="0" top="0" horiadvance="0" />
     <rectangle x="0" y="56" width="8" height="8" char="し" left="0" top="0" horiadvance="0" />
     <rectangle x="8" y="56" width="8" height="8" char="す" left="0" top="0" horiadvance="0" />
     <rectangle x="16" y="56" width="8" height="8" char="せ" left="0" top="0" horiadvance="0" />
     <rectangle x="24" y="56" width="8" height="8" char="そ" left="0" top="0" horiadvance="0" />
     <rectangle x="32" y="56" width="8" height="8" char="た" left="0" top="0" horiadvance="0" />
     <rectangle x="40" y="56" width="8" height="8" char="ち" left="0" top="0" horiadvance="0" />
     <rectangle x="48" y="56" width="8" height="8" char="つ" left="0" top="0" horiadvance="0" />
     <rectangle x="56" y="56" width="8" height="8" char="て" left="0" top="0" horiadvance="0" />
     <rectangle x="64" y="56" width="8" height="8" char="と" left="0" top="0" horiadvance="0" />
     <rectangle x="72" y="56" width="8" height="8" char="な" left="0" top="0" horiadvance="0" />
     <rectangle x="80" y="56" width="8" height="8" char="に" left="0" top="0" horiadvance="0" />
     <rectangle x="88" y="56" width="8" height="8" char="ぬ" left="0" top="0" horiadvance="0" />
     <rectangle x="96" y="56" width="8" height="8" char="ね" left="0" top="0" horiadvance="0" />
     <rectangle x="104" y="56" width="8" height="8" char="の" left="0" top="0" horiadvance="0" />
     <rectangle x="112" y="56" width="8" height="8" char="は" left="0" top="0" horiadvance="0" />
     <rectangle x="120" y="56" width="8" height="8" char="ひ" left="0" top="0" horiadvance="0" />
     <rectangle x="0" y="64" width="8" height="8" char="ふ" left="0" top="0" horiadvance="0" />
     <rectangle x="8" y="64" width="8" height="8" char="へ" left="0" top="0" horiadvance="0" />
     <rectangle x="16" y="64" width="8" height="8" char="ほ" left="0" top="0" horiadvance="0" />
     <rectangle x="24" y="64" width="8" height="8" char="ま" left="0" top="1" horiadvance="0" />
     <rectangle x="32" y="64" width="8" height="8" char="み" left="0" top="0" horiadvance="0" />
     <rectangle x="40" y="64" width="8" height="8" char="む" left="0" top="0" horiadvance="0" />
     <rectangle x="48" y="64" width="8" height="8" char="め" left="0" top="0" horiadvance="0" />
     <rectangle x="56" y="64" width="8" height="8" char="も" left="0" top="0" horiadvance="0" />
     <rectangle x="64" y="64" width="8" height="8" char="や" left="0" top="0" horiadvance="0" />
     <rectangle x="72" y="64" width="8" height="8" char="ゆ" left="0" top="0" horiadvance="0" />
     <rectangle x="80" y="64" width="8" height="8" char="よ" left="0" top="0" horiadvance="0" />
     <rectangle x="88" y="64" width="8" height="8" char="ら" left="0" top="0" horiadvance="0" />
     <rectangle x="96" y="64" width="8" height="8" char="り" left="0" top="0" horiadvance="0" />
     <rectangle x="104" y="64" width="8" height="8" char="る" left="0" top="0" horiadvance="0" />
     <rectangle x="112" y="64" width="8" height="8" char="れ" left="0" top="0" horiadvance="0" />
     <rectangle x="120" y="64" width="8" height="8" char="ろ" left="0" top="0" horiadvance="0" />
     <rectangle x="0" y="72" width="8" height="8" char="わ" left="0" top="1" horiadvance="0" />
     <rectangle x="8" y="72" width="8" height="8" char="を" left="0" top="1" horiadvance="0" />
     <rectangle x="16" y="72" width="8" height="8" char="ん" left="0" top="0" horiadvance="0" />
     <rectangle x="24" y="72" width="8" height="8" char="ゃ" left="0" top="0" horiadvance="0" />
     <rectangle x="32" y="72" width="8" height="8" char="ゅ" left="0" top="0" horiadvance="0" />
     <rectangle x="40" y="72" width="8" height="8" char="ょ" left="0" top="0" horiadvance="0" />
     <rectangle x="48" y="72" width="8" height="8" char="っ" left="0" top="0" horiadvance="0" />
     <rectangle x="56" y="72" width="8" height="8" char="が" left="0" top="1" horiadvance="0" />
     <rectangle x="64" y="72" width="8" height="8" char="ぎ" left="0" top="1" horiadvance="0" />
     <rectangle x="72" y="72" width="8" height="8" char="ぐ" left="0" top="1" horiadvance="0" />
     <rectangle x="80" y="72" width="8" height="8" char="げ" left="0" top="1" horiadvance="0" />
     <rectangle x="88" y="72" width="8" height="8" char="ご" left="0" top="1" horiadvance="0" />
     <rectangle x="96" y="72" width="8" height="8" char="ざ" left="0" top="1" horiadvance="0" />
     <rectangle x="104" y="72" width="8" height="8" char="じ" left="0" top="1" horiadvance="0" />
     <rectangle x="112" y="72" width="8" height="8" char="ず" left="0" top="1" horiadvance="0" />
     <rectangle x="120" y="72" width="8" height="8" char="ぜ" left="0" top="1" horiadvance="0" />
     <rectangle x="0" y="80" width="8" height="8" char="ぞ" left="0" top="1" horiadvance="0" />
     <rectangle x="8" y="80" width="8" height="8" char="だ" left="0" top="1" horiadvance="0" />
     <rectangle x="16" y="80" width="8" height="8" char="ぢ" left="0" top="1" horiadvance="0" />
     <rectangle x="24" y="80" width="8" height="8" char="づ" left="0" top="1" horiadvance="0" />
     <rectangle x="32" y="80" width="8" height="8" char="で" left="0" top="1" horiadvance="0" />
     <rectangle x="40" y="80" width="8" height="8" char="ど" left="0" top="1" horiadvance="0" />
     <rectangle x="48" y="80" width="8" height="8" char="ば" left="0" top="1" horiadvance="0" />
     <rectangle x="56" y="80" width="8" height="8" char="び" left="0" top="1" horiadvance="0" />
     <rectangle x="64" y="80" width="8" height="8" char="ぶ" left="0" top="1" horiadvance="0" />
     <rectangle x="72" y="80" width="8" height="8" char="べ" left="0" top="1" horiadvance="0" />
     <rectangle x="80" y="80" width="8" height="8" char="ぼ" left="0" top="1" horiadvance="0" />
     <rectangle x="88" y="80" width="8" height="8" char="ぱ" left="0" top="1" horiadvance="0" />
     <rectangle x="96" y="80" width="8" height="8" char="ぴ" left="0" top="1" horiadvance="0" />
     <rectangle x="104" y="80" width="8" height="8" char="ぷ" left="0" top="1" horiadvance="0" />
     <rectangle x="112" y="80" width="8" height="8" char="ぺ" left="0" top="1" horiadvance="0" />
     <rectangle x="120" y="80" width="8" height="8" char="ぽ" left="0" top="1" horiadvance="0" />
     <rectangle x="0" y="88" width="8" height="8" char="ア" left="0" top="0" horiadvance="0" />
     <rectangle x="8" y="88" width="8" height="8" char="イ" left="0" top="0" horiadvance="0" />
     <rectangle x="16" y="88" width="8" height="8" char="ウ" left="0" top="0" horiadvance="0" />
     <rectangle x="24" y="88" width="8" height="8" char="エ" left="0" top="0" horiadvance="0" />
     <rectangle x="32" y="88" width="8" height="8" char="オ" left="0" top="0" horiadvance="0" />
     <rectangle x="40" y="88" width="8" height="8" char="カ" left="0" top="0" horiadvance="0" />
     <rectangle x="48" y="88" width="8" height="8" char="キ" left="0" top="0" horiadvance="0" />
     <rectangle x="56" y="88" width="8" height="8" char="ク" left="0" top="0" horiadvance="0" />
     <rectangle x="64" y="88" width="8" height="8" char="ケ" left="0" top="0" horiadvance="0" />
     <rectangle x="72" y="88" width="8" height="8" char="コ" left="0" top="0" horiadvance="0" />
     <rectangle x="80" y="88" width="8" height="8" char="サ" left="0" top="0" horiadvance="0" />
     <rectangle x="88" y="88" width="8" height="8" char="シ" left="0" top="0" horiadvance="0" />
     <rectangle x="96" y="88" width="8" height="8" char="ス" left="0" top="0" horiadvance="0" />
     <rectangle x="104" y="88" width="8" height="8" char="セ" left="0" top="0" horiadvance="0" />
     <rectangle x="112" y="88" width="8" height="8" char="ソ" left="0" top="0" horiadvance="0" />
     <rectangle x="120" y="88" width="8" height="8" char="タ" left="0" top="0" horiadvance="0" />
     <rectangle x="0" y="96" width="8" height="8" char="チ" left="0" top="0" horiadvance="0" />
     <rectangle x="8" y="96" width="8" height="8" char="ツ" left="0" top="0" horiadvance="0" />
     <rectangle x="16" y="96" width="8" height="8" char="テ" left="0" top="0" horiadvance="0" />
     <rectangle x="24" y="96" width="8" height="8" char="ト" left="0" top="0" horiadvance="0" />
     <rectangle x="32" y="96" width="8" height="8" char="ナ" left="0" top="0" horiadvance="0" />
     <rectangle x="40" y="96" width="8" height="8" char="ニ" left="0" top="0" horiadvance="0" />
     <rectangle x="48" y="96" width="8" height="8" char="ヌ" left="0" top="0" horiadvance="0" />
     <rectangle x="56" y="96" width="8" height="8" char="ネ" left="0" top="0" horiadvance="0" />
     <rectangle x="64" y="96" width="8" height="8" char="ノ" left="0" top="0" horiadvance="0" />
     <rectangle x="72" y="96" width="8" height="8" char="ハ" left="0" top="0" horiadvance="0" />
     <rectangle x="80" y="96" width="8" height="8" char="ヒ" left="0" top="0" horiadvance="0" />
     <rectangle x="88" y="96" width="8" height="8" char="フ" left="0" top="0" horiadvance="0" />
     <rectangle x="96" y="96" width="8" height="8" char="ヘ" left="0" top="0" horiadvance="0" />
     <rectangle x="104" y="96" width="8" height="8" char="ホ" left="0" top="0" horiadvance="0" />
     <rectangle x="112" y="96" width="8" height="8" char="マ" left="0" top="0" horiadvance="0" />
     <rectangle x="120" y="96" width="8" height="8" char="ミ" left="0" top="0" horiadvance="0" />
     <rectangle x="0" y="104" width="8" height="8" char="ム" left="0" top="0" horiadvance="0" />
     <rectangle x="8" y="104" width="8" height="8" char="メ" left="0" top="0" horiadvance="0" />
     <rectangle x="16" y="104" width="8" height="8" char="モ" left="0" top="0" horiadvance="0" />
     <rectangle x="24" y="104" width="8" height="8" char="ヤ" left="0" top="0" horiadvance="0" />
     <rectangle x="32" y="104" width="8" height="8" char="ユ" left="0" top="0" horiadvance="0" />
     <rectangle x="40" y="104" width="8" height="8" char="ヨ" left="0" top="0" horiadvance="0" />
     <rectangle x="48" y="104" width="8" height="8" char="ラ" left="0" top="0" horiadvance="0" />
     <rectangle x="56" y="104" width="8" height="8" char="リ" left="0" top="0" horiadvance="0" />
     <rectangle x="64" y="104" width="8" height="8" char="ル" left="0" top="0" horiadvance="0" />
     <rectangle x="72" y="104" width="8" height="8" char="レ" left="0" top="0" horiadvance="0" />
     <rectangle x="80" y="104" width="8" height="8" char="ロ" left="0" top="0" horiadvance="0" />
     <rectangle x="88" y="104" width="8" height="8" char="ワ" left="0" top="0" horiadvance="0" />
     <rectangle x="96" y="104" width="8" height="8" char="ヲ" left="0" top="0" horiadvance="0" />
     <rectangle x="104" y="104" width="8" height="8" char="ン" left="0" top="0" horiadvance="0" />
     <rectangle x="112" y="104" width="8" height="8" char="ァ" left="0" top="0" horiadvance="0" />
     <rectangle x="120" y="104" width="8" height="8" char="ィ" left="0" top="0" horiadvance="0" />
     <rectangle x="0" y="112" width="8" height="8" char="ゥ" left="0" top="0" horiadvance="0" />
     <rectangle x="8" y="112" width="8" height="8" char="ェ" left="0" top="0" horiadvance="0" />
     <rectangle x="16" y="112" width="8" height="8" char="ォ" left="0" top="0" horiadvance="0" />
     <rectangle x="24" y="112" width="8" height="8" char="ャ" left="0" top="0" horiadvance="0" />
     <rectangle x="32" y="112" width="8" height="8" char="ュ" left="0" top="0" horiadvance="0" />
     <rectangle x="40" y="112" width="8" height="8" char="ョ" left="0" top="0" horiadvance="0" />
     <rectangle x="48" y="112" width="8" height="8" char="ッ" left="0" top="0" horiadvance="0" />
     <rectangle x="56" y="112" width="8" height="8" char="ガ" left="0" top="1" horiadvance="0" />
     <rectangle x="64" y="112" width="8" height="8" char="ギ" left="0" top="1" horiadvance="0" />
     <rectangle x="72" y="112" width="8" height="8" char="グ" left="0" top="1" horiadvance="0" />
     <rectangle x="80" y="112" width="8" height="8" char="ゲ" left="0" top="1" horiadvance="0" />
     <rectangle x="88" y="112" width="8" height="8" char="ゴ" left="0" top="1" horiadvance="0" />
     <rectangle x="96" y="112" width="8" height="8" char="ザ" left="0" top="1" horiadvance="0" />
     <rectangle x="104" y="112" width="8" height="8" char="ジ" left="0" top="1" horiadvance="0" />
     <rectangle x="112" y="112" width="8" height="8" char="ズ" left="0" top="1" horiadvance="0" />
     <rectangle x="120" y="112" width="8" height="8" char="ゼ" left="0" top="1" horiadvance="0" />
     <rectangle x="0" y="120" width="8" height="8" char="ゾ" left="0" top="1" horiadvance="0" />
     <rectangle x="8" y="120" width="8" height="8" char="ダ" left="0" top="1" horiadvance="0" />
     <rectangle x="16" y="120" width="8" height="8" char="ヂ" left="0" top="1" horiadvance="0" />
     <rectangle x="24" y="120" width="8" height="8" char="ヅ" left="0" top="1" horiadvance="0" />
     <rectangle x="32" y="120" width="8" height="8" char="デ" left="0" top="1" horiadvance="0" />
     <rectangle x="40" y="120" width="8" height="8" char="ド" left="0" top="1" horiadvance="0" />
     <rectangle x="48" y="120" width="8" height="8" char="バ" left="0" top="1" horiadvance="0" />
     <rectangle x="56" y="120" width="8" height="8" char="ビ" left="0" top="1" horiadvance="0" />
     <rectangle x="64" y="120" width="8" height="8" char="ブ" left="0" top="1" horiadvance="0" />
     <rectangle x="72" y="120" width="8" height="8" char="ベ" left="0" top="1" horiadvance="0" />
     <rectangle x="80" y="120" width="8" height="8" char="ボ" left="0" top="1" horiadvance="0" />
     <rectangle x="88" y="120" width="8" height="8" char="パ" left="0" top="1" horiadvance="0" />
     <rectangle x="96" y="120" width="8" height="8" char="ピ" left="0" top="1" horiadvance="0" />
     <rectangle x="104" y="120" width="8" height="8" char="プ" left="0" top="1" horiadvance="0" />
     <rectangle x="112" y="120" width="8" height="8" char="ペ" left="0" top="1" horiadvance="0" />
     <rectangle x="120" y="120" width="8" height="8" char="ポ" left="0" top="1" horiadvance="0" />
	 
	 <!-- ENGLISH -->
	   <rectangle x="0" y="0" width="8" height="8" char="A" left="0" top="0" horiadvance="0" />
     <rectangle x="8" y="0" width="8" height="8" char="B" left="0" top="0" horiadvance="0" />
     <rectangle x="16" y="0" width="8" height="8" char="C" left="0" top="0" horiadvance="0" />
     <rectangle x="24" y="0" width="8" height="8" char="D" left="0" top="0" horiadvance="0" />
     <rectangle x="32" y="0" width="8" height="8" char="E" left="0" top="0" horiadvance="0" />
     <rectangle x="40" y="0" width="8" height="8" char="F" left="0" top="0" horiadvance="0" />
     <rectangle x="48" y="0" width="8" height="8" char="G" left="0" top="0" horiadvance="0" />
     <rectangle x="56" y="0" width="8" height="8" char="H" left="0" top="0" horiadvance="0" />
     <rectangle x="64" y="0" width="8" height="8" char="I" left="0" top="0" horiadvance="0" />
     <rectangle x="72" y="0" width="8" height="8" char="J" left="0" top="0" horiadvance="0" />
     <rectangle x="80" y="0" width="8" height="8" char="K" left="0" top="0" horiadvance="0" />
     <rectangle x="88" y="0" width="8" height="8" char="L" left="0" top="0" horiadvance="0" />
     <rectangle x="96" y="0" width="8" height="8" char="M" left="0" top="0" horiadvance="0" />
     <rectangle x="104" y="0" width="8" height="8" char="N" left="0" top="0" horiadvance="0" />
     <rectangle x="112" y="0" width="8" height="8" char="O" left="0" top="0" horiadvance="0" />
     <rectangle x="120" y="0" width="8" height="8" char="P" left="0" top="0" horiadvance="0" />
     <rectangle x="0" y="8" width="8" height="8" char="Q" left="0" top="0" horiadvance="0" />
     <rectangle x="8" y="8" width="8" height="8" char="R" left="0" top="0" horiadvance="0" />
     <rectangle x="16" y="8" width="8" height="8" char="S" left="0" top="0" horiadvance="0" />
     <rectangle x="24" y="8" width="8" height="8" char="T" left="0" top="0" horiadvance="0" />
     <rectangle x="32" y="8" width="8" height="8" char="U" left="0" top="0" horiadvance="0" />
     <rectangle x="40" y="8" width="8" height="8" char="V" left="0" top="0" horiadvance="0" />
     <rectangle x="48" y="8" width="8" height="8" char="W" left="0" top="0" horiadvance="0" />
     <rectangle x="56" y="8" width="8" height="8" char="X" left="0" top="0" horiadvance="0" />
     <rectangle x="64" y="8" width="8" height="8" char="Y" left="0" top="0" horiadvance="0" />
     <rectangle x="72" y="8" width="8" height="8" char="Z" left="0" top="0" horiadvance="0" />
     <rectangle x="80" y="8" width="8" height="8" char="a" left="0" top="0" horiadvance="0" />
     <rectangle x="88" y="8" width="8" height="8" char="b" left="0" top="0" horiadvance="0" />
     <rectangle x="96" y="8" width="8" height="8" char="c" left="0" top="0" horiadvance="0" />
     <rectangle x="104" y="8" width="8" height="8" char="d" left="0" top="0" horiadvance="0" />
     <rectangle x="112" y="8" width="8" height="8" char="e" left="0" top="0" horiadvance="0" />
     <rectangle x="120" y="8" width="8" height="8" char="f" left="0" top="0" horiadvance="0" />
     <rectangle x="0" y="16" width="8" height="8" char="g" left="0" top="0" horiadvance="0" />
     <rectangle x="8" y="16" width="8" height="8" char="h" left="0" top="0" horiadvance="0" />
     <rectangle x="16" y="16" width="8" height="8" char="i" left="0" top="0" horiadvance="0" />
     <rectangle x="24" y="16" width="8" height="8" char="j" left="0" top="0" horiadvance="0" />
     <rectangle x="32" y="16" width="8" height="8" char="k" left="0" top="0" horiadvance="0" />
     <rectangle x="40" y="16" width="8" height="8" char="l" left="0" top="0" horiadvance="0" />
     <rectangle x="48" y="16" width="8" height="8" char="m" left="0" top="0" horiadvance="0" />
     <rectangle x="56" y="16" width="8" height="8" char="n" left="0" top="0" horiadvance="0" />
     <rectangle x="64" y="16" width="8" height="8" char="o" left="0" top="0" horiadvance="0" />
     <rectangle x="72" y="16" width="8" height="8" char="p" left="0" top="0" horiadvance="0" />
     <rectangle x="80" y="16" width="8" height="8" char="q" left="0" top="0" horiadvance="0" />
     <rectangle x="88" y="16" width="8" height="8" char="r" left="0" top="0" horiadvance="0" />
     <rectangle x="96" y="16" width="8" height="8" char="s" left="0" top="0" horiadvance="0" />
     <rectangle x="104" y="16" width="8" height="8" char="t" left="0" top="0" horiadvance="0" />
     <rectangle x="112" y="16" width="8" height="8" char="u" left="0" top="0" horiadvance="0" />
     <rectangle x="120" y="16" width="8" height="8" char="v" left="0" top="0" horiadvance="0" />
     <rectangle x="0" y="24" width="8" height="8" char="w" left="0" top="0" horiadvance="0" />
     <rectangle x="8" y="24" width="8" height="8" char="x" left="0" top="0" horiadvance="0" />
     <rectangle x="16" y="24" width="8" height="8" char="y" left="0" top="0" horiadvance="0" />
     <rectangle x="24" y="24" width="8" height="8" char="z" left="0" top="0" horiadvance="0" />
     <rectangle x="32" y="24" width="8" height="8" char="0" left="0" top="0" horiadvance="0" />
     <rectangle x="40" y="24" width="8" height="8" char="1" left="0" top="0" horiadvance="0" />
     <rectangle x="48" y="24" width="8" height="8" char="2" left="0" top="0" horiadvance="0" />
     <rectangle x="56" y="24" width="8" height="8" char="3" left="0" top="0" horiadvance="0" />
     <rectangle x="64" y="24" width="8" height="8" char="4" left="0" top="0" horiadvance="0" />
     <rectangle x="72" y="24" width="8" height="8" char="5" left="0" top="0" horiadvance="0" />
     <rectangle x="80" y="24" width="8" height="8" char="6" left="0" top="0" horiadvance="0" />
     <rectangle x="88" y="24" width="8" height="8" char="7" left="0" top="0" horiadvance="0" />
     <rectangle x="96" y="24" width="8" height="8" char="8" left="0" top="0" horiadvance="0" />
     <rectangle x="104" y="24" width="8" height="8" char="9" left="0" top="0" horiadvance="0" />
     <rectangle x="0" y="32" width="8" height="8" char="." left="0" top="0" horiadvance="0" />
     <rectangle x="8" y="32" width="8" height="8" char=":" left="0" top="0" horiadvance="0" />
     <rectangle x="16" y="32" width="8" height="8" char=";" left="0" top="0" horiadvance="0" />
     <rectangle x="24" y="32" width="8" height="8" char="?" left="0" top="0" horiadvance="0" />
     <rectangle x="32" y="32" width="8" height="8" char="!" left="0" top="0" horiadvance="0" />
	 
	 <rectangle x="64" y="32" width="8" height="8" char="(" left="0" top="0" horiadvance="0" />
     <rectangle x="72" y="32" width="8" height="8" char=")" left="0" top="0" horiadvance="0" />
     <rectangle x="80" y="32" width="8" height="8" char="<" left="0" top="0" horiadvance="0" />
     <rectangle x="88" y="32" width="8" height="8" char=">" left="0" top="0" horiadvance="0" />
	 
	 <rectangle x="112" y="32" width="8" height="8" char="[" left="0" top="0" horiadvance="0" />
     <rectangle x="120" y="32" width="8" height="8" char="]" left="0" top="0" horiadvance="0" />
	 
	 <rectangle x="0" y="40" width="8" height="8" char="+" left="0" top="0" horiadvance="0" />
     <rectangle x="8" y="40" width="8" height="8" char="-" left="0" top="0" horiadvance="0" />
     <rectangle x="24" y="32" width="8" height="8" char="?" left="0" top="0" horiadvance="0" />
     <rectangle x="24" y="40" width="8" height="8" char="%" left="0" top="0" horiadvance="0" />
     <rectangle x="32" y="40" width="8" height="8" char="#" left="0" top="0" horiadvance="0" />
     <rectangle x="40" y="40" width="8" height="8" char="$" left="0" top="0" horiadvance="0" />
     <rectangle x="48" y="40" width="8" height="8" char="&" left="0" top="0" horiadvance="0" />
     <rectangle x="56" y="40" width="8" height="8" char="*" left="0" top="0" horiadvance="0" />
	 
  </characters>
</spritefont>